pytest_dataguard/___init__.py
pytest_dataguard/options.py
pytest_dataguard/plugin.py
pytest_dataguard/tests/test_plugin.py
pytest_dataguard-1.0.3.dist-info/METADATA
pytest_dataguard-1.0.3.dist-info/WHEEL
pytest_dataguard-1.0.3.dist-info/entry_points.txt
pytest_dataguard-1.0.3.dist-info/top_level.txt
pytest_dataguard-1.0.3.dist-info/RECORD
