Metadata-Version: 2.4
Name: pytest-dataguard
Version: 1.0.3
Summary: Data validation and integrity testing for your datasets using pytest.
Author-email: Ola Austine <austineolanrewaju@gmail.com>
Project-URL: Homepage, https://github.com/olaaustine/pytest_dataguard
Project-URL: Issues, https://github.com/olaaustine/pytest_dataguard/issues
Keywords: pytest,plugin,data,quality,csv,polars
Classifier: Framework :: Pytest
Classifier: Programming Language :: Python :: 3
Classifier: Operating System :: OS Independent
Requires-Python: >=3.10
Requires-Dist: pip>=25.2
Requires-Dist: polars>=1.34.0
Requires-Dist: pre-commit>=4.3.0
Requires-Dist: pytest>=8.4.2
